pgtui/__init__.py
pgtui/__main__.py
pgtui/app.css
pgtui/app.py
pgtui/bindings.py
pgtui/cli.py
pgtui/completer.py
pgtui/config.py
pgtui/db.py
pgtui/entities.py
pgtui/messages.py
pgtui/sql.py
pgtui/utils/__init__.py
pgtui/utils/datetime.py
pgtui/utils/string.py
pgtui/widgets/__init__.py
pgtui/widgets/autocomplete.py
pgtui/widgets/containers.py
pgtui/widgets/dialog.py
pgtui/widgets/export.py
pgtui/widgets/footer.py
pgtui/widgets/list_view.py
pgtui/widgets/menu.py
pgtui/widgets/modal.py
pgtui/widgets/pane.py
pgtui/widgets/results.py
pgtui/widgets/status_bar.py
pgtui/widgets/tabbed_content.py
pgtui/widgets/text_area.py
pgtui-0.21.1.dist-info/licenses/LICENSE
pgtui-0.21.1.dist-info/METADATA
pgtui-0.21.1.dist-info/WHEEL
pgtui-0.21.1.dist-info/entry_points.txt
pgtui-0.21.1.dist-info/top_level.txt
pgtui-0.21.1.dist-info/RECORD
