Metadata-Version: 2.4
Name: pgtui
Version: 0.21.1
Summary: PostgreSQL terminal user interface
Author-email: Ivan Habunek <ivan@habunek.com>
License: Copyright 2024 pgtui contributors
Project-URL: Homepage, https://codeberg.org/ihabunek/pgtui
Classifier: Programming Language :: Python :: 3
Classifier: License :: OSI Approved :: MIT License
Classifier: Operating System :: OS Independent
Classifier: Environment :: Console
Requires-Python: >=3.11
License-File: LICENSE
Requires-Dist: click
Requires-Dist: pgcli
Requires-Dist: psycopg[binary]
Requires-Dist: sqlparse
Requires-Dist: textual-fspicker~=0.1
Requires-Dist: textual[syntax]~=3.4
Requires-Dist: tree-sitter-sql==0.3.7
Dynamic: license-file
